mt5_wrapper/__init__.py
mt5_wrapper/constants.py
mt5_wrapper/data_structures.py
mt5_wrapper/wraps.py
mt5_wrapper-1.0.8.dist-info/METADATA
mt5_wrapper-1.0.8.dist-info/WHEEL
mt5_wrapper-1.0.8.dist-info/top_level.txt
mt5_wrapper-1.0.8.dist-info/RECORD
