Metadata-Version: 2.2
Name: mt5-wrapper
Version: 1.0.8
Summary: A Python package that enhances the MetaTrader5 library by adding type annotations and IntelliSense support for better code readability, auto-complete, and improved developer experience.
License: MIT
Project-URL: homepage, https://github.com/imrbrad/mt5_wrapper
Project-URL: repository, https://github.com/imrbrad/mt5_wrapper
Requires-Python: >=3.13
Requires-Dist: metatrader5>=5.0.4874
